   {
        "last_name": "Pike",
        "updated_at": 1358373602.0,
        "sources": [
            {
                "url": "http://www.leg.wa.gov/house/representatives/Pages/pike.aspx"
            }
        ],
        "full_name": "Liz Pike",
        "first_name": "Liz",
        "middle_name": "",
        "district": "18",
        "_code": "17158",
        "state": "wa",
        "party": "Republican",
        "_type": "person",
        "_scraped_name": "Liz Pike",
        "leg_id": "WAL000176",
        "active": true,
        "photo_url": "http://www.leg.wa.gov/house/representatives/publishingimages/pike.jpg",
        "roles": [
            {
                "term": "2013-2014",
                "end_date": null,
                "district": "18",
                "chamber": "lower",
                "state": "wa",
                "party": "Republican",
                "type": "member",
                "start_date": null
            }
        ],
        "_all_ids": [
            "WAL000176"
        ],
        "url": "http://www.leg.wa.gov/house/representatives/Pages/pike.aspx",
        "created_at": 1358302774.0,
        "chamber": "lower",
        "offices": [
            {
                "fax": null,
                "name": "Olympia Office",
                "phone": "(360) 786-7812",
                "address": "122B Legislative Building\nPO Box 40600\nOlympia, WA 98504-0600",
                "type": "capitol",
                "email": null
            }
        ],
        "_id": "WAL000176",
        "suffixes": ""
    },